MANIFEST.in
README.txt
setup.cfg
setup.py
docs/HISTORY.txt
docs/LICENSE.GPL
docs/LICENSE.txt
docs/MANUAL.txt
raptus/__init__.py
raptus.article.multilanguagefields.egg-info/PKG-INFO
raptus.article.multilanguagefields.egg-info/SOURCES.txt
raptus.article.multilanguagefields.egg-info/dependency_links.txt
raptus.article.multilanguagefields.egg-info/entry_points.txt
raptus.article.multilanguagefields.egg-info/namespace_packages.txt
raptus.article.multilanguagefields.egg-info/not-zip-safe
raptus.article.multilanguagefields.egg-info/requires.txt
raptus.article.multilanguagefields.egg-info/top_level.txt
raptus/article/__init__.py
raptus/article/multilanguagefields/__init__.py
raptus/article/multilanguagefields/configure.zcml
raptus/article/multilanguagefields/modifier.py
raptus/article/multilanguagefields/setuphandlers.py
raptus/article/multilanguagefields/Extensions/Install.py
raptus/article/multilanguagefields/Extensions/__init__.py
raptus/article/multilanguagefields/profiles/default/metadata.xml
raptus/article/multilanguagefields/profiles/default/raptus.article.multilanguagefields_install.txt
raptus/article/multilanguagefields/profiles/uninstall/import_steps.xml
raptus/article/multilanguagefields/profiles/uninstall/raptus.article.multilanguagefields_uninstall.txt