Metadata-Version: 1.0
Name: raptus.article.multilanguagefields
Version: 2.0b11
Summary: Provides support for raptus.multilanguagefields in article
Home-page: http://raptus.com
Author: Raptus AG
Author-email: dev@raptus.com
License: GPL
Platform: UNKNOWN
Classifier: Programming Language :: Python
